ci_plumber/__init__.py
ci_plumber/__main__.py
ci_plumber/docs/README.md
ci_plumber/docs/__init__.py
ci_plumber/helpers/__init__.py
ci_plumber/helpers/config_helpers.py
ci_plumber/helpers/file_generators.py
ci_plumber/helpers/git_helpers.py
ci_plumber/helpers/run_command.py
ci_plumber/main.py
ci_plumber/module_attributes.py
ci_plumber/templates/__init__.py
ci_plumber/templates/gitlab-ci-azure.yml
ci_plumber/templates/gitlab-ci.yml
ci_plumber/templates/maria.json
ci_plumber-1.4.2.dist-info/entry_points.txt
ci_plumber-1.4.2.dist-info/WHEEL
ci_plumber-1.4.2.dist-info/METADATA
ci_plumber-1.4.2.dist-info/RECORD
