Metadata-Version: 2.1
Name: ci-plumber
Version: 1.4.2
Summary: Plumb together different CI/CD services
Home-page: https://github.com/pbexe/ci-plumber
Author: Miles Budden
Author-email: git@miles.so
Requires-Python: >=3.9,<4.0
Classifier: Development Status :: 4 - Beta
Classifier: Environment :: Console
Classifier: Environment :: Other Environment
Classifier: Intended Audience :: Developers
Classifier: Intended Audience :: Education
Classifier: Operating System :: Microsoft :: Windows
Classifier: Operating System :: POSIX
Classifier: Programming Language :: Python :: 3
Classifier: Programming Language :: Python :: 3.9
Classifier: Typing :: Typed
Provides-Extra: all
Requires-Dist: GitPython (>=3.1.20,<4.0.0)
Requires-Dist: ci-plumber-azure (>=0.2.3,<0.3.0); extra == "all"
Requires-Dist: ci-plumber-gitlab (>=0.1.3,<0.2.0); extra == "all"
Requires-Dist: ci-plumber-openshift (>=0.3.1,<0.4.0); extra == "all"
Requires-Dist: framework-detector (>=0.2.1,<0.3.0)
Requires-Dist: importlib-metadata (>=4.6.3,<5.0.0)
Requires-Dist: openshift (>=0.12.1,<0.13.0)
Requires-Dist: python-gitlab (>=2.10.0,<3.0.0)
Requires-Dist: rich (>=10.7.0,<11.0.0)
Requires-Dist: typer[all] (>=0.3.2,<0.4.0)
Requires-Dist: types-requests (>=2.25.2,<3.0.0)
Project-URL: Repository, https://github.com/pbexe/ci-plumber
